[
  {
    "id": "INFANTRY",
    "name": "Infantry",
    "distance": 2,
    "canTraverseWaterTiles": false,
    "baseHp": 80,
    "baseAtkByRange": {
      "1": 42,
      "2": 28
    }
  },
  {
    "id": "CAVALRY",
    "name": "Cavalry",
    "distance": 3,
    "canTraverseWaterTiles": false,
    "baseHp": 80,
    "baseAtkByRange": {
      "1": 36,
      "2": 24
    }
  },
  {
    "id": "FLYING",
    "name": "Flying",
    "distance": 2,
    "canTraverseWaterTiles": true,
    "baseHp": 80,
    "baseAtkByRange": {
      "1": 36,
      "2": 24
    }
  },
  {
    "id": "ARMORED",
    "name": "Armored",
    "distance": 2,
    "canTraverseWaterTiles": false,
    "baseHp": 88,
    "baseAtkByRange": {
      "1": 30,
      "2": 20
    }
  }
]
